{"proj_pecota_batting": {"queryResults": {"created": "2019-09-14T17:17:42", "totalSize": "0"}}, "copyRight": " Copyright 2019 MLB Advanced Media, L.P.  Use of any content on this page acknowledges agreement to the terms posted here http://gdx.mlb.com/components/copyright.txt  ", "sport_career_hitting": {"queryResults": {"created": "2019-09-14T17:30:44", "totalSize": "6", "row": [{"hr": "0", "gidp": "0", "np": "1", "sac": "0", "team_count": "1", "sport_code": "aaa", "hgnd": "0", "rbi": "0", "lob": "0", "babip": "1.000", "gidp_opp": "0", "tb": "2", "xbh": "1", "sport_id": "11", "bb": "0", "avg": "1.000", "slg": "2.000", "ops": "3.000", "hbp": "0", "g": "1", "d": "1", "hfly": "0", "so": "0", "wo": "0", "sport": "AAA", "sf": "0", "hpop": "0", "tpa": "1", "h": "1", "cs": "0", "obp": "1.000", "hldr": "1", "t": "0", "ao": "0", "r": "1", "go_ao": "", "sb": "0", "ppa": "1.00", "player_id": "593800", "ab": "1", "ibb": "0", "roe": "0", "go": "0"}, {"hr": "3", "gidp": "8", "np": "1635", "sac": "2", "team_count": "1", "sport_code": "aax", "hgnd": "26", "rbi": "32", "lob": "211", "babip": ".305", "gidp_opp": "50", "tb": "123", "xbh": "25", "sport_id": "12", "bb": "29", "avg": ".225", "slg": ".308", "ops": ".597", "hbp": "8", "g": "128", "d": "20", "hfly": "19", "so": "114", "wo": "0", "sport": "AA", "sf": "2", "hpop": "0", "tpa": "441", "h": "90", "cs": "1", "obp": ".289", "hldr": "45", "t": "2", "ao": "111", "r": "38", "go_ao": "0.82", "sb": "1", "ppa": "3.71", "player_id": "593800", "ab": "400", "ibb": "2", "roe": "2", "go": "91"}, {"hr": "9", "gidp": "9", "np": "647", "sac": "3", "team_count": "2", "sport_code": "afa", "hgnd": "40", "rbi": "52", "lob": "211", "babip": ".335", "gidp_opp": "59", "tb": "197", "xbh": "38", "sport_id": "13", "bb": "73", "avg": ".268", "slg": ".385", "ops": ".751", "hbp": "10", "g": "156", "d": "25", "hfly": "36", "so": "126", "wo": "1", "sport": "A(Adv)", "sf": "5", "hpop": "0", "tpa": "603", "h": "137", "cs": "8", "obp": ".367", "hldr": "61", "t": "4", "ao": "138", "r": "71", "go_ao": "0.93", "sb": "18", "ppa": "1.07", "player_id": "593800", "ab": "512", "ibb": "0", "roe": "9", "go": "128"}, {"hr": "9", "gidp": "13", "np": "431", "sac": "7", "team_count": "2", "sport_code": "afx", "hgnd": "72", "rbi": "71", "lob": "366", "babip": ".312", "gidp_opp": "123", "tb": "305", "xbh": "61", "sport_id": "14", "bb": "86", "avg": ".256", "slg": ".358", "ops": ".692", "hbp": "19", "g": "227", "d": "44", "hfly": "55", "so": "182", "wo": "1", "sport": "A(Full)", "sf": "7", "hpop": "3", "tpa": "972", "h": "218", "cs": "11", "obp": ".335", "hldr": "88", "t": "8", "ao": "239", "r": "110", "go_ao": "1.01", "sb": "30", "ppa": "0.44", "player_id": "593800", "ab": "853", "ibb": "0", "roe": "14", "go": "241"}, {"hr": "8", "gidp": "1", "np": "", "sac": "2", "team_count": "1", "sport_code": "asx", "hgnd": "37", "rbi": "33", "lob": "78", "babip": ".360", "gidp_opp": "31", "tb": "135", "xbh": "26", "sport_id": "15", "bb": "33", "avg": ".298", "slg": ".496", "ops": ".877", "hbp": "6", "g": "69", "d": "6", "hfly": "22", "so": "65", "wo": "0", "sport": "A(Short)", "sf": "4", "hpop": "0", "tpa": "317", "h": "81", "cs": "5", "obp": ".381", "hldr": "22", "t": "12", "ao": "65", "r": "61", "go_ao": "1.05", "sb": "15", "ppa": "0.00", "player_id": "593800", "ab": "272", "ibb": "1", "roe": "6", "go": "68"}, {"hr": "1", "gidp": "5", "np": "224", "sac": "9", "team_count": "2", "sport_code": "rok", "hgnd": "60", "rbi": "65", "lob": "160", "babip": ".380", "gidp_opp": "72", "tb": "188", "xbh": "31", "sport_id": "16", "bb": "41", "avg": ".326", "slg": ".425", "ops": ".819", "hbp": "13", "g": "121", "d": "19", "hfly": "40", "so": "72", "wo": "1", "sport": "ROK", "sf": "7", "hpop": "1", "tpa": "512", "h": "144", "cs": "16", "obp": ".394", "hldr": "43", "t": "11", "ao": "126", "r": "70", "go_ao": "0.96", "sb": "31", "ppa": "0.44", "player_id": "593800", "ab": "442", "ibb": "1", "roe": "9", "go": "121"}]}}, "sport_hitting_tm": {"queryResults": {"created": "2019-09-14T17:30:44", "totalSize": "10", "row": [{"gidp": "3", "sac": "5", "np": "224", "sport_code": "rok", "hgnd": "31", "tb": "84", "gidp_opp": "37", "sport_id": "16", "bb": "28", "avg": ".282", "slg": ".353", "team_full": "DSL Cubs1", "ops": ".728", "hbp": "10", "league_full": "Dominican Summer League", "team_abbrev": "DSL CUB", "so": "33", "hfly": "24", "wo": "1", "league_id": "130", "sf": "4", "team_seq": "1", "league": "DSL", "hpop": "0", "cs": "8", "season": "2010", "sb": "18", "go_ao": "0.65", "ppa": "0.79", "player_id": "593800", "ibb": "0", "team_id": "609", "roe": "5", "go": "59", "hr": "1", "rbi": "29", "babip": ".317", "lob": "89", "end_date": "2011-05-26T00:00:00", "xbh": "12", "league_short": "Dominican Summer", "g": "69", "d": "8", "sport": "ROK", "team_short": "DSL Cubs1", "tpa": "285", "h": "67", "obp": ".375", "hldr": "12", "t": "3", "ao": "91", "r": "33", "ab": "238"}, {"gidp": "2", "sac": "4", "np": "", "sport_code": "rok", "hgnd": "29", "tb": "104", "gidp_opp": "35", "sport_id": "16", "bb": "13", "avg": ".377", "slg": ".510", "team_full": "AZL Cubs", "ops": ".927", "hbp": "3", "league_full": "Arizona League", "team_abbrev": "CUB", "so": "39", "hfly": "16", "wo": "0", "league_id": "121", "sf": "3", "team_seq": "1", "league": "AZL", "hpop": "1", "cs": "8", "season": "2011", "sb": "13", "go_ao": "1.77", "ppa": "0.00", "player_id": "593800", "ibb": "1", "team_id": "407", "roe": "4", "go": "62", "hr": "0", "rbi": "36", "babip": ".458", "lob": "71", "end_date": "2012-05-11T00:00:00", "xbh": "19", "league_short": "Arizona", "g": "52", "d": "11", "sport": "ROK", "team_short": "AZL Cubs", "tpa": "227", "h": "77", "obp": ".417", "hldr": "31", "t": "8", "ao": "35", "r": "37", "ab": "204"}, {"gidp": "0", "sac": "0", "np": "1", "sport_code": "aaa", "hgnd": "0", "tb": "2", "gidp_opp": "0", "sport_id": "11", "bb": "0", "avg": "1.000", "slg": "2.000", "team_full": "Iowa Cubs", "ops": "3.000", "hbp": "0", "league_full": "Pacific Coast League", "team_abbrev": "IOW", "so": "0", "hfly": "0", "wo": "0", "league_id": "112", "sf": "0", "team_seq": "1", "league": "PCL", "hpop": "0", "cs": "0", "season": "2012", "sb": "0", "go_ao": "-.--", "ppa": "1.00", "player_id": "593800", "ibb": "0", "team_id": "451", "roe": "0", "go": "0", "hr": "0", "rbi": "0", "babip": "1.000", "lob": "0", "end_date": "2012-05-16T00:00:00", "xbh": "1", "league_short": "Pacific Coast", "g": "1", "d": "1", "sport": "AAA", "team_short": "Iowa", "tpa": "1", "h": "1", "obp": "1.000", "hldr": "1", "t": "0", "ao": "0", "r": "1", "ab": "1"}, {"gidp": "1", "sac": "2", "np": "", "sport_code": "asx", "hgnd": "37", "tb": "135", "gidp_opp": "31", "sport_id": "15", "bb": "33", "avg": ".298", "slg": ".496", "team_full": "Boise Hawks", "ops": ".877", "hbp": "6", "league_full": "Northwest League", "team_abbrev": "BOI", "so": "65", "hfly": "22", "wo": "0", "league_id": "126", "sf": "4", "team_seq": "1", "league": "NOR", "hpop": "0", "cs": "5", "season": "2012", "sb": "15", "go_ao": "1.05", "ppa": "0.00", "player_id": "593800", "ibb": "1", "team_id": "480", "roe": "6", "go": "68", "hr": "8", "rbi": "33", "babip": ".360", "lob": "78", "end_date": "2013-03-31T00:00:00", "xbh": "26", "league_short": "Northwest", "g": "69", "d": "6", "sport": "A(Short)", "team_short": "Boise", "tpa": "317", "h": "81", "obp": ".381", "hldr": "22", "t": "12", "ao": "65", "r": "61", "ab": "272"}, {"gidp": "7", "sac": "3", "np": "226", "sport_code": "afx", "hgnd": "39", "tb": "167", "gidp_opp": "68", "sport_id": "14", "bb": "42", "avg": ".252", "slg": ".369", "team_full": "Kane County Cougars", "ops": ".698", "hbp": "13", "league_full": "Midwest League", "team_abbrev": "KC", "so": "109", "hfly": "26", "wo": "0", "league_id": "118", "sf": "5", "team_seq": "1", "league": "MID", "hpop": "3", "cs": "6", "season": "2013", "sb": "13", "go_ao": "0.96", "ppa": "0.44", "player_id": "593800", "ibb": "0", "team_id": "446", "roe": "9", "go": "120", "hr": "5", "rbi": "28", "babip": ".317", "lob": "199", "end_date": "2014-03-29T00:00:00", "xbh": "37", "league_short": "Midwest", "g": "117", "d": "26", "sport": "A(Full)", "team_short": "Kane County", "tpa": "516", "h": "114", "obp": ".329", "hldr": "46", "t": "6", "ao": "125", "r": "65", "ab": "453"}, {"gidp": "6", "sac": "2", "np": "44", "sport_code": "afa", "hgnd": "32", "tb": "136", "gidp_opp": "43", "sport_id": "13", "bb": "53", "avg": ".276", "slg": ".369", "team_full": "Daytona Cubs", "ops": ".747", "hbp": "9", "league_full": "Florida State League", "team_abbrev": "DAY", "so": "90", "hfly": "29", "wo": "1", "league_id": "123", "sf": "2", "team_seq": "1", "league": "FSL", "hpop": "0", "cs": "7", "season": "2014", "sb": "14", "go_ao": "0.99", "ppa": "0.10", "player_id": "593800", "ibb": "0", "team_id": "450", "roe": "9", "go": "93", "hr": "4", "rbi": "35", "babip": ".354", "lob": "150", "end_date": "2014-09-16T00:00:00", "xbh": "23", "league_short": "Florida State", "g": "112", "d": "16", "sport": "A(Adv)", "team_short": "Daytona", "tpa": "435", "h": "102", "obp": ".379", "hldr": "41", "t": "3", "ao": "94", "r": "56", "ab": "369"}, {"gidp": "6", "sac": "4", "np": "205", "sport_code": "afx", "hgnd": "33", "tb": "138", "gidp_opp": "55", "sport_id": "14", "bb": "44", "avg": ".260", "slg": ".345", "team_full": "South Bend Cubs", "ops": ".686", "hbp": "6", "league_full": "Midwest League", "team_abbrev": "SB", "so": "73", "hfly": "29", "wo": "1", "league_id": "118", "sf": "2", "team_seq": "1", "league": "MID", "hpop": "0", "cs": "5", "season": "2015", "sb": "17", "go_ao": "1.06", "ppa": "0.45", "player_id": "593800", "ibb": "0", "team_id": "550", "roe": "5", "go": "121", "hr": "4", "rbi": "43", "babip": ".308", "lob": "167", "end_date": "2016-04-05T00:00:00", "xbh": "24", "league_short": "Midwest", "g": "110", "d": "18", "sport": "A(Full)", "team_short": "South Bend", "tpa": "456", "h": "104", "obp": ".341", "hldr": "42", "t": "2", "ao": "114", "r": "45", "ab": "400"}, {"gidp": "3", "sac": "1", "np": "603", "sport_code": "afa", "hgnd": "8", "tb": "61", "gidp_opp": "16", "sport_id": "13", "bb": "20", "avg": ".245", "slg": ".427", "team_full": "Myrtle Beach Pelicans", "ops": ".762", "hbp": "1", "league_full": "Carolina League", "team_abbrev": "MB", "so": "36", "hfly": "7", "wo": "0", "league_id": "122", "sf": "3", "team_seq": "1", "league": "CAR", "hpop": "0", "cs": "1", "season": "2016", "sb": "4", "go_ao": "0.80", "ppa": "3.59", "player_id": "593800", "ibb": "0", "team_id": "521", "roe": "0", "go": "35", "hr": "5", "rbi": "17", "babip": ".286", "lob": "61", "end_date": "2016-06-24T00:00:00", "xbh": "15", "league_short": "Carolina", "g": "44", "d": "9", "sport": "A(Adv)", "team_short": "Myrtle Beach", "tpa": "168", "h": "35", "obp": ".335", "hldr": "20", "t": "1", "ao": "44", "r": "15", "ab": "143"}, {"gidp": "2", "sac": "0", "np": "584", "sport_code": "aax", "hgnd": "6", "tb": "31", "gidp_opp": "19", "sport_id": "12", "bb": "13", "avg": ".183", "slg": ".237", "team_full": "Tennessee Smokies", "ops": ".504", "hbp": "2", "league_full": "Southern League", "team_abbrev": "TNS", "so": "43", "hfly": "3", "wo": "0", "league_id": "111", "sf": "0", "team_seq": "1", "league": "SOU", "hpop": "0", "cs": "1", "season": "2016", "sb": "0", "go_ao": "0.61", "ppa": "4.00", "player_id": "593800", "ibb": "0", "team_id": "553", "roe": "0", "go": "25", "hr": "1", "rbi": "8", "babip": ".264", "lob": "78", "end_date": "2017-04-02T00:00:00", "xbh": "4", "league_short": "Southern", "g": "44", "d": "2", "sport": "AA", "team_short": "Tennessee", "tpa": "146", "h": "24", "obp": ".267", "hldr": "15", "t": "1", "ao": "41", "r": "12", "ab": "131"}, {"gidp": "6", "sac": "2", "np": "1051", "sport_code": "aax", "hgnd": "20", "tb": "92", "gidp_opp": "31", "sport_id": "12", "bb": "16", "avg": ".245", "slg": ".342", "team_full": "Tennessee Smokies", "ops": ".642", "hbp": "6", "league_full": "Southern League", "team_abbrev": "TNS", "so": "71", "hfly": "16", "wo": "0", "league_id": "111", "sf": "2", "team_seq": "1", "league": "SOU", "hpop": "0", "cs": "0", "season": "2019", "sb": "1", "go_ao": "0.94", "ppa": "3.56", "player_id": "593800", "ibb": "2", "team_id": "553", "roe": "2", "go": "66", "hr": "2", "rbi": "24", "babip": ".323", "lob": "133", "end_date": "2019-09-14T00:00:00", "xbh": "21", "league_short": "Southern", "g": "84", "d": "18", "sport": "AA", "team_short": "Tennessee", "tpa": "295", "h": "66", "obp": ".300", "hldr": "30", "t": "1", "ao": "70", "r": "26", "ab": "269"}]}}, "sport_career_hitting_agg": {"queryResults": {"created": "2019-09-14T17:30:44", "totalSize": "1", "row": {"hr": "30", "gidp": "36", "np": "2938", "sac": "23", "team_count": "9", "sport_code": "min", "hgnd": "235", "rbi": "253", "lob": "1026", "babip": ".335", "gidp_opp": "335", "tb": "950", "xbh": "182", "sport_id": "21", "bb": "262", "avg": ".271", "slg": ".383", "ops": ".733", "hbp": "56", "g": "702", "d": "115", "hfly": "172", "so": "559", "wo": "3", "sport": "Minors", "sf": "25", "hpop": "4", "tpa": "2846", "h": "671", "cs": "41", "obp": ".350", "hldr": "260", "t": "37", "ao": "679", "r": "351", "go_ao": "0.96", "sb": "95", "ppa": "1.03", "player_id": "593800", "ab": "2480", "ibb": "4", "roe": "40", "go": "649"}}}, "sport_hitting_agg": {"queryResults": {"created": "2019-09-14T17:30:44", "totalSize": "8", "row": [{"hr": "1", "gidp": "3", "np": "224", "sac": "5", "team_count": "1", "popout": "33", "sport_code": "min", "hgnd": "31", "rbi": "29", "lob": "89", "babip": ".317", "gidp_opp": "37", "tb": "84", "xbh": "12", "sport_id": "21", "bb": "28", "avg": ".282", "slg": ".353", "ops": ".728", "hbp": "10", "g": "69", "d": "8", "lineout": "7", "hfly": "24", "so": "33", "flyout": "51", "wo": "1", "sport": "Minors", "sf": "4", "hpop": "0", "tpa": "285", "h": "67", "cs": "8", "obp": ".375", "hldr": "12", "t": "3", "ao": "91", "season": "2010", "r": "33", "go_ao": "0.65", "sb": "18", "ppa": "0.79", "player_id": "593800", "ab": "238", "ibb": "0", "roe": "5", "go": "59"}, {"hr": "0", "gidp": "2", "np": "", "sac": "4", "team_count": "1", "popout": "9", "sport_code": "min", "hgnd": "29", "rbi": "36", "lob": "71", "babip": ".458", "gidp_opp": "35", "tb": "104", "xbh": "19", "sport_id": "21", "bb": "13", "avg": ".377", "slg": ".510", "ops": ".927", "hbp": "3", "g": "52", "d": "11", "lineout": "4", "hfly": "16", "so": "39", "flyout": "22", "wo": "0", "sport": "Minors", "sf": "3", "hpop": "1", "tpa": "227", "h": "77", "cs": "8", "obp": ".417", "hldr": "31", "t": "8", "ao": "35", "season": "2011", "r": "37", "go_ao": "1.77", "sb": "13", "ppa": "0.00", "player_id": "593800", "ab": "204", "ibb": "1", "roe": "4", "go": "62"}, {"hr": "8", "gidp": "1", "np": "1", "sac": "2", "team_count": "2", "popout": "19", "sport_code": "min", "hgnd": "37", "rbi": "33", "lob": "78", "babip": ".363", "gidp_opp": "31", "tb": "137", "xbh": "27", "sport_id": "21", "bb": "33", "avg": ".300", "slg": ".502", "ops": ".885", "hbp": "6", "g": "70", "d": "7", "lineout": "5", "hfly": "22", "so": "65", "flyout": "41", "wo": "0", "sport": "Minors", "sf": "4", "hpop": "0", "tpa": "318", "h": "82", "cs": "5", "obp": ".383", "hldr": "23", "t": "12", "ao": "65", "season": "2012", "r": "62", "go_ao": "1.05", "sb": "15", "ppa": "0.00", "player_id": "593800", "ab": "273", "ibb": "1", "roe": "6", "go": "68"}, {"hr": "5", "gidp": "7", "np": "226", "sac": "3", "team_count": "1", "popout": "21", "sport_code": "min", "hgnd": "39", "rbi": "28", "lob": "199", "babip": ".317", "gidp_opp": "68", "tb": "167", "xbh": "37", "sport_id": "21", "bb": "42", "avg": ".252", "slg": ".369", "ops": ".698", "hbp": "13", "g": "117", "d": "26", "lineout": "15", "hfly": "26", "so": "109", "flyout": "89", "wo": "0", "sport": "Minors", "sf": "5", "hpop": "3", "tpa": "516", "h": "114", "cs": "6", "obp": ".329", "hldr": "46", "t": "6", "ao": "125", "season": "2013", "r": "65", "go_ao": "0.96", "sb": "13", "ppa": "0.44", "player_id": "593800", "ab": "453", "ibb": "0", "roe": "9", "go": "120"}, {"hr": "4", "gidp": "6", "np": "44", "sac": "2", "team_count": "1", "popout": "13", "sport_code": "min", "hgnd": "32", "rbi": "35", "lob": "150", "babip": ".354", "gidp_opp": "43", "tb": "136", "xbh": "23", "sport_id": "21", "bb": "53", "avg": ".276", "slg": ".369", "ops": ".747", "hbp": "9", "g": "112", "d": "16", "lineout": "10", "hfly": "29", "so": "90", "flyout": "71", "wo": "1", "sport": "Minors", "sf": "2", "hpop": "0", "tpa": "435", "h": "102", "cs": "7", "obp": ".379", "hldr": "41", "t": "3", "ao": "94", "season": "2014", "r": "56", "go_ao": "0.99", "sb": "14", "ppa": "0.10", "player_id": "593800", "ab": "369", "ibb": "0", "roe": "9", "go": "93"}, {"hr": "4", "gidp": "6", "np": "205", "sac": "4", "team_count": "1", "popout": "33", "sport_code": "min", "hgnd": "33", "rbi": "43", "lob": "167", "babip": ".308", "gidp_opp": "55", "tb": "138", "xbh": "24", "sport_id": "21", "bb": "44", "avg": ".260", "slg": ".345", "ops": ".686", "hbp": "6", "g": "110", "d": "18", "lineout": "17", "hfly": "29", "so": "73", "flyout": "64", "wo": "1", "sport": "Minors", "sf": "2", "hpop": "0", "tpa": "456", "h": "104", "cs": "5", "obp": ".341", "hldr": "42", "t": "2", "ao": "114", "season": "2015", "r": "45", "go_ao": "1.06", "sb": "17", "ppa": "0.45", "player_id": "593800", "ab": "400", "ibb": "0", "roe": "5", "go": "121"}, {"hr": "6", "gidp": "5", "np": "1187", "sac": "1", "team_count": "2", "popout": "20", "sport_code": "min", "hgnd": "14", "rbi": "25", "lob": "139", "babip": ".276", "gidp_opp": "35", "tb": "92", "xbh": "19", "sport_id": "21", "bb": "33", "avg": ".215", "slg": ".336", "ops": ".639", "hbp": "3", "g": "88", "d": "11", "lineout": "12", "hfly": "10", "so": "79", "flyout": "53", "wo": "0", "sport": "Minors", "sf": "3", "hpop": "0", "tpa": "314", "h": "59", "cs": "2", "obp": ".304", "hldr": "35", "t": "2", "ao": "85", "season": "2016", "r": "27", "go_ao": "0.71", "sb": "4", "ppa": "3.78", "player_id": "593800", "ab": "274", "ibb": "0", "roe": "0", "go": "60"}, {"hr": "2", "gidp": "6", "np": "1051", "sac": "2", "team_count": "1", "popout": "11", "sport_code": "min", "hgnd": "20", "rbi": "24", "lob": "133", "babip": ".323", "gidp_opp": "31", "tb": "92", "xbh": "21", "sport_id": "21", "bb": "16", "avg": ".245", "slg": ".342", "ops": ".642", "hbp": "6", "g": "84", "d": "18", "lineout": "5", "hfly": "16", "so": "71", "flyout": "54", "wo": "0", "sport": "Minors", "sf": "2", "hpop": "0", "tpa": "295", "h": "66", "cs": "0", "obp": ".300", "hldr": "30", "t": "1", "ao": "70", "season": "2019", "r": "26", "go_ao": "0.94", "sb": "1", "ppa": "3.56", "player_id": "593800", "ab": "269", "ibb": "2", "roe": "2", "go": "66"}]}}, "sport_career_hitting_lg": {"queryResults": {"created": "2019-09-14T17:30:44", "totalSize": "8", "row": [{"hr": "0", "gidp": "0", "sac": "0", "team_count": "1", "sport_code": "aaa", "rbi": "0", "tb": "2", "sport_id": "11", "bb": "0", "avg": "1.000", "slg": "2.000", "league_short": "Pacific Coast", "ops": "3.000", "hbp": "0", "g": "1", "league_full": "Pacific Coast League", "d": "1", "so": "0", "league_id": "112", "sport": "AAA", "sf": "0", "league": "PCL", "h": "1", "cs": "0", "obp": "1.000", "t": "0", "ao": "0", "r": "1", "go_ao": "", "sb": "0", "player_id": "593800", "ab": "1", "ibb": "0", "go": "0"}, {"hr": "3", "gidp": "8", "sac": "2", "team_count": "1", "sport_code": "aax", "rbi": "32", "tb": "123", "sport_id": "12", "bb": "29", "avg": ".225", "slg": ".308", "league_short": "Southern", "ops": ".597", "hbp": "8", "g": "128", "league_full": "Southern League", "d": "20", "so": "114", "league_id": "111", "sport": "AA", "sf": "2", "league": "SOU", "h": "90", "cs": "1", "obp": ".289", "t": "2", "ao": "111", "r": "38", "go_ao": "0.82", "sb": "1", "player_id": "593800", "ab": "400", "ibb": "2", "go": "91"}, {"hr": "5", "gidp": "3", "sac": "1", "team_count": "1", "sport_code": "afa", "rbi": "17", "tb": "61", "sport_id": "13", "bb": "20", "avg": ".245", "slg": ".427", "league_short": "Carolina", "ops": ".762", "hbp": "1", "g": "44", "league_full": "Carolina League", "d": "9", "so": "36", "league_id": "122", "sport": "A(Adv)", "sf": "3", "league": "CAR", "h": "35", "cs": "1", "obp": ".335", "t": "1", "ao": "44", "r": "15", "go_ao": "0.80", "sb": "4", "player_id": "593800", "ab": "143", "ibb": "0", "go": "35"}, {"hr": "4", "gidp": "6", "sac": "2", "team_count": "1", "sport_code": "afa", "rbi": "35", "tb": "136", "sport_id": "13", "bb": "53", "avg": ".276", "slg": ".369", "league_short": "Florida State", "ops": ".747", "hbp": "9", "g": "112", "league_full": "Florida State League", "d": "16", "so": "90", "league_id": "123", "sport": "A(Adv)", "sf": "2", "league": "FSL", "h": "102", "cs": "7", "obp": ".379", "t": "3", "ao": "94", "r": "56", "go_ao": "0.99", "sb": "14", "player_id": "593800", "ab": "369", "ibb": "0", "go": "93"}, {"hr": "9", "gidp": "13", "sac": "7", "team_count": "2", "sport_code": "afx", "rbi": "71", "tb": "305", "sport_id": "14", "bb": "86", "avg": ".256", "slg": ".358", "league_short": "Midwest", "ops": ".692", "hbp": "19", "g": "227", "league_full": "Midwest League", "d": "44", "so": "182", "league_id": "118", "sport": "A(Full)", "sf": "7", "league": "MID", "h": "218", "cs": "11", "obp": ".335", "t": "8", "ao": "239", "r": "110", "go_ao": "1.01", "sb": "30", "player_id": "593800", "ab": "853", "ibb": "0", "go": "241"}, {"hr": "8", "gidp": "1", "sac": "2", "team_count": "1", "sport_code": "asx", "rbi": "33", "tb": "135", "sport_id": "15", "bb": "33", "avg": ".298", "slg": ".496", "league_short": "Northwest", "ops": ".877", "hbp": "6", "g": "69", "league_full": "Northwest League", "d": "6", "so": "65", "league_id": "126", "sport": "A(Short)", "sf": "4", "league": "NOR", "h": "81", "cs": "5", "obp": ".381", "t": "12", "ao": "65", "r": "61", "go_ao": "1.05", "sb": "15", "player_id": "593800", "ab": "272", "ibb": "1", "go": "68"}, {"hr": "0", "gidp": "2", "sac": "4", "team_count": "1", "sport_code": "rok", "rbi": "36", "tb": "104", "sport_id": "16", "bb": "13", "avg": ".377", "slg": ".510", "league_short": "Arizona", "ops": ".927", "hbp": "3", "g": "52", "league_full": "Arizona League", "d": "11", "so": "39", "league_id": "121", "sport": "ROK", "sf": "3", "league": "AZL", "h": "77", "cs": "8", "obp": ".417", "t": "8", "ao": "35", "r": "37", "go_ao": "1.77", "sb": "13", "player_id": "593800", "ab": "204", "ibb": "1", "go": "62"}, {"hr": "1", "gidp": "3", "sac": "5", "team_count": "1", "sport_code": "rok", "rbi": "29", "tb": "84", "sport_id": "16", "bb": "28", "avg": ".282", "slg": ".353", "league_short": "Dominican Summer", "ops": ".728", "hbp": "10", "g": "69", "league_full": "Dominican Summer League", "d": "8", "so": "33", "league_id": "130", "sport": "ROK", "sf": "4", "league": "DSL", "h": "67", "cs": "8", "obp": ".375", "t": "3", "ao": "91", "r": "33", "go_ao": "0.65", "sb": "18", "player_id": "593800", "ab": "238", "ibb": "0", "go": "59"}]}}, "proj_pecota_ros_batting": {"queryResults": {"created": "2019-09-14T17:17:42", "totalSize": "0"}}, "index": 3339}