{"proj_pecota_batting": {"queryResults": {"created": "2019-09-14T18:00:27", "totalSize": "0"}}, "copyRight": " Copyright 2019 MLB Advanced Media, L.P.  Use of any content on this page acknowledges agreement to the terms posted here http://gdx.mlb.com/components/copyright.txt  ", "sport_career_hitting": {"queryResults": {"created": "2019-09-14T18:00:27", "totalSize": "6", "row": [{"hr": "0", "gidp": "0", "np": "9", "sac": "0", "team_count": "1", "sport_code": "aaa", "hgnd": "1", "rbi": "0", "lob": "0", "babip": ".500", "gidp_opp": "0", "tb": "2", "xbh": "0", "sport_id": "11", "bb": "0", "avg": ".500", "slg": ".500", "ops": "1.000", "hbp": "0", "g": "1", "d": "0", "hfly": "0", "so": "0", "wo": "0", "sport": "AAA", "sf": "0", "hpop": "0", "tpa": "4", "h": "2", "cs": "0", "obp": ".500", "hldr": "1", "t": "0", "ao": "0", "r": "3", "go_ao": "2.00", "sb": "0", "ppa": "2.25", "player_id": "642451", "ab": "4", "ibb": "0", "roe": "1", "go": "2"}, {"hr": "2", "gidp": "1", "np": "849", "sac": "2", "team_count": "2", "sport_code": "aax", "hgnd": "20", "rbi": "18", "lob": "95", "babip": ".291", "gidp_opp": "29", "tb": "64", "xbh": "13", "sport_id": "12", "bb": "15", "avg": ".225", "slg": ".314", "ops": ".592", "hbp": "0", "g": "55", "d": "10", "hfly": "3", "so": "51", "wo": "2", "sport": "AA", "sf": "0", "hpop": "0", "tpa": "221", "h": "46", "cs": "1", "obp": ".279", "hldr": "23", "t": "1", "ao": "51", "r": "25", "go_ao": "1.16", "sb": "4", "ppa": "3.84", "player_id": "642451", "ab": "204", "ibb": "0", "roe": "2", "go": "59"}, {"hr": "26", "gidp": "13", "np": "2969", "sac": "10", "team_count": "1", "sport_code": "afa", "hgnd": "76", "rbi": "101", "lob": "345", "babip": ".308", "gidp_opp": "125", "tb": "323", "xbh": "69", "sport_id": "13", "bb": "75", "avg": ".260", "slg": ".430", "ops": ".756", "hbp": "2", "g": "199", "d": "36", "hfly": "56", "so": "184", "wo": "1", "sport": "A(Adv)", "sf": "7", "hpop": "1", "tpa": "845", "h": "195", "cs": "11", "obp": ".326", "hldr": "62", "t": "7", "ao": "182", "r": "114", "go_ao": "1.20", "sb": "13", "ppa": "3.51", "player_id": "642451", "ab": "751", "ibb": "4", "roe": "14", "go": "219"}, {"hr": "8", "gidp": "8", "np": "2362", "sac": "18", "team_count": "1", "sport_code": "afx", "hgnd": "59", "rbi": "51", "lob": "257", "babip": ".318", "gidp_opp": "96", "tb": "229", "xbh": "51", "sport_id": "14", "bb": "72", "avg": ".243", "slg": ".386", "ops": ".709", "hbp": "0", "g": "165", "d": "25", "hfly": "40", "so": "161", "wo": "0", "sport": "A(Full)", "sf": "4", "hpop": "0", "tpa": "687", "h": "144", "cs": "6", "obp": ".323", "hldr": "45", "t": "18", "ao": "121", "r": "102", "go_ao": "1.63", "sb": "10", "ppa": "3.44", "player_id": "642451", "ab": "593", "ibb": "1", "roe": "14", "go": "197"}, {"hr": "5", "gidp": "3", "np": "86", "sac": "7", "team_count": "1", "sport_code": "asx", "hgnd": "13", "rbi": "31", "lob": "79", "babip": ".318", "gidp_opp": "36", "tb": "82", "xbh": "20", "sport_id": "15", "bb": "24", "avg": ".260", "slg": ".453", "ops": ".794", "hbp": "0", "g": "53", "d": "10", "hfly": "13", "so": "47", "wo": "0", "sport": "A(Short)", "sf": "3", "hpop": "0", "tpa": "215", "h": "47", "cs": "3", "obp": ".341", "hldr": "21", "t": "5", "ao": "42", "r": "34", "go_ao": "1.38", "sb": "10", "ppa": "0.40", "player_id": "642451", "ab": "181", "ibb": "0", "roe": "6", "go": "58"}, {"hr": "4", "gidp": "1", "np": "", "sac": "6", "team_count": "2", "sport_code": "rok", "hgnd": "34", "rbi": "31", "lob": "147", "babip": ".304", "gidp_opp": "47", "tb": "127", "xbh": "24", "sport_id": "16", "bb": "52", "avg": ".235", "slg": ".335", "ops": ".667", "hbp": "4", "g": "106", "d": "14", "hfly": "30", "so": "97", "wo": "0", "sport": "ROK", "sf": "2", "hpop": "1", "tpa": "443", "h": "89", "cs": "10", "obp": ".332", "hldr": "24", "t": "6", "ao": "102", "r": "67", "go_ao": "0.98", "sb": "28", "ppa": "0.00", "player_id": "642451", "ab": "379", "ibb": "0", "roe": "10", "go": "100"}]}}, "sport_hitting_tm": {"queryResults": {"created": "2019-09-14T18:00:27", "totalSize": "12", "row": [{"gidp": "1", "sac": "2", "np": "", "sport_code": "rok", "hgnd": "19", "tb": "72", "gidp_opp": "25", "sport_id": "16", "bb": "23", "avg": ".255", "slg": ".353", "team_full": "DSL Mariners", "ops": ".691", "hbp": "3", "league_full": "Dominican Summer League", "team_abbrev": "DSL SEA", "so": "50", "hfly": "20", "wo": "0", "league_id": "130", "sf": "1", "team_seq": "1", "league": "DSL", "hpop": "1", "cs": "8", "season": "2013", "sb": "14", "go_ao": "0.89", "ppa": "0.00", "player_id": "642451", "ibb": "0", "team_id": "618", "roe": "5", "go": "50", "hr": "2", "rbi": "17", "babip": ".327", "lob": "74", "end_date": "2014-05-26T00:00:00", "xbh": "13", "league_short": "Dominican Summer", "g": "57", "d": "8", "sport": "ROK", "team_short": "DSL Mariners", "tpa": "233", "h": "52", "obp": ".338", "hldr": "12", "t": "3", "ao": "56", "r": "39", "ab": "204"}, {"gidp": "0", "sac": "4", "np": "", "sport_code": "rok", "hgnd": "15", "tb": "55", "gidp_opp": "22", "sport_id": "16", "bb": "29", "avg": ".211", "slg": ".314", "team_full": "AZL Mariners", "ops": ".640", "hbp": "1", "league_full": "Arizona League", "team_abbrev": "MAR", "so": "47", "hfly": "10", "wo": "0", "league_id": "121", "sf": "1", "team_seq": "1", "league": "AZL", "hpop": "0", "cs": "2", "season": "2014", "sb": "14", "go_ao": "1.09", "ppa": "0.00", "player_id": "642451", "ibb": "0", "team_id": "409", "roe": "5", "go": "50", "hr": "2", "rbi": "14", "babip": ".276", "lob": "73", "end_date": "2015-05-01T00:00:00", "xbh": "11", "league_short": "Arizona", "g": "49", "d": "6", "sport": "ROK", "team_short": "AZL Mariners", "tpa": "210", "h": "37", "obp": ".325", "hldr": "12", "t": "3", "ao": "46", "r": "28", "ab": "175"}, {"gidp": "2", "sac": "0", "np": "", "sport_code": "afx", "hgnd": "1", "tb": "7", "gidp_opp": "8", "sport_id": "14", "bb": "2", "avg": ".133", "slg": ".233", "team_full": "Clinton LumberKings", "ops": ".421", "hbp": "0", "league_full": "Midwest League", "team_abbrev": "CLI", "so": "10", "hfly": "2", "wo": "0", "league_id": "118", "sf": "0", "team_seq": "1", "league": "MID", "hpop": "0", "cs": "0", "season": "2015", "sb": "1", "go_ao": "2.00", "ppa": "0.00", "player_id": "642451", "ibb": "0", "team_id": "500", "roe": "1", "go": "12", "hr": "0", "rbi": "0", "babip": ".200", "lob": "12", "end_date": "2015-05-11T00:00:00", "xbh": "2", "league_short": "Midwest", "g": "8", "d": "1", "sport": "A(Full)", "team_short": "Clinton", "tpa": "32", "h": "4", "obp": ".188", "hldr": "1", "t": "1", "ao": "6", "r": "3", "ab": "30"}, {"gidp": "1", "sac": "0", "np": "35", "sport_code": "aax", "hgnd": "0", "tb": "0", "gidp_opp": "3", "sport_id": "12", "bb": "0", "avg": ".000", "slg": ".000", "team_full": "Jackson Generals", "ops": ".000", "hbp": "0", "league_full": "Southern League", "team_abbrev": "JXN", "so": "2", "hfly": "0", "wo": "0", "league_id": "111", "sf": "0", "team_seq": "1", "league": "SOU", "hpop": "0", "cs": "0", "season": "2015", "sb": "0", "go_ao": "2.00", "ppa": "3.50", "player_id": "642451", "ibb": "0", "team_id": "104", "roe": "1", "go": "6", "hr": "0", "rbi": "0", "babip": ".000", "lob": "8", "end_date": "2015-06-12T00:00:00", "xbh": "0", "league_short": "Southern", "g": "3", "d": "0", "sport": "AA", "team_short": "Jackson", "tpa": "10", "h": "0", "obp": ".000", "hldr": "0", "t": "0", "ao": "3", "r": "0", "ab": "10"}, {"gidp": "3", "sac": "7", "np": "86", "sport_code": "asx", "hgnd": "13", "tb": "82", "gidp_opp": "36", "sport_id": "15", "bb": "24", "avg": ".260", "slg": ".453", "team_full": "Everett AquaSox", "ops": ".794", "hbp": "0", "league_full": "Northwest League", "team_abbrev": "EVE", "so": "47", "hfly": "13", "wo": "0", "league_id": "126", "sf": "3", "team_seq": "1", "league": "NWL", "hpop": "0", "cs": "3", "season": "2015", "sb": "10", "go_ao": "1.38", "ppa": "0.40", "player_id": "642451", "ibb": "0", "team_id": "403", "roe": "6", "go": "58", "hr": "5", "rbi": "31", "babip": ".318", "lob": "79", "end_date": "2016-04-02T00:00:00", "xbh": "20", "league_short": "Northwest", "g": "53", "d": "10", "sport": "A(Short)", "team_short": "Everett", "tpa": "215", "h": "47", "obp": ".341", "hldr": "21", "t": "5", "ao": "42", "r": "34", "ab": "181"}, {"gidp": "5", "sac": "12", "np": "1577", "sport_code": "afx", "hgnd": "44", "tb": "137", "gidp_opp": "60", "sport_id": "14", "bb": "47", "avg": ".258", "slg": ".368", "team_full": "Clinton LumberKings", "ops": ".709", "hbp": "0", "league_full": "Midwest League", "team_abbrev": "CLI", "so": "100", "hfly": "19", "wo": "0", "league_id": "118", "sf": "1", "team_seq": "1", "league": "MID", "hpop": "0", "cs": "2", "season": "2016", "sb": "4", "go_ao": "2.13", "ppa": "3.65", "player_id": "642451", "ibb": "1", "team_id": "500", "roe": "9", "go": "132", "hr": "2", "rbi": "29", "babip": ".347", "lob": "166", "end_date": "2017-06-16T00:00:00", "xbh": "29", "league_short": "Midwest", "g": "100", "d": "19", "sport": "A(Full)", "team_short": "Clinton", "tpa": "432", "h": "96", "obp": ".340", "hldr": "33", "t": "8", "ao": "62", "r": "65", "ab": "372"}, {"gidp": "1", "sac": "6", "np": "785", "sport_code": "afx", "hgnd": "14", "tb": "85", "gidp_opp": "28", "sport_id": "14", "bb": "23", "avg": ".230", "slg": ".445", "team_full": "Clinton LumberKings", "ops": ".754", "hbp": "0", "league_full": "Midwest League", "team_abbrev": "CLI", "so": "51", "hfly": "19", "wo": "0", "league_id": "118", "sf": "3", "team_seq": "1", "league": "MID", "hpop": "0", "cs": "4", "season": "2017", "sb": "5", "go_ao": "1.00", "ppa": "3.52", "player_id": "642451", "ibb": "0", "team_id": "500", "roe": "4", "go": "53", "hr": "6", "rbi": "22", "babip": ".277", "lob": "79", "end_date": "2017-06-17T00:00:00", "xbh": "20", "league_short": "Midwest", "g": "57", "d": "5", "sport": "A(Full)", "team_short": "Clinton", "tpa": "223", "h": "44", "obp": ".309", "hldr": "11", "t": "9", "ao": "53", "r": "34", "ab": "191"}, {"gidp": "4", "sac": "3", "np": "954", "sport_code": "afa", "hgnd": "23", "tb": "111", "gidp_opp": "35", "sport_id": "13", "bb": "21", "avg": ".257", "slg": ".432", "team_full": "Modesto Nuts", "ops": ".746", "hbp": "1", "league_full": "California League", "team_abbrev": "MOD", "so": "80", "hfly": "21", "wo": "0", "league_id": "110", "sf": "1", "team_seq": "1", "league": "CAL", "hpop": "1", "cs": "4", "season": "2017", "sb": "7", "go_ao": "1.13", "ppa": "3.37", "player_id": "642451", "ibb": "2", "team_id": "515", "roe": "1", "go": "63", "hr": "8", "rbi": "28", "babip": ".341", "lob": "129", "end_date": "2018-04-01T00:00:00", "xbh": "24", "league_short": "California", "g": "68", "d": "11", "sport": "A(Adv)", "team_short": "Modesto", "tpa": "283", "h": "66", "obp": ".314", "hldr": "21", "t": "5", "ao": "56", "r": "41", "ab": "257"}, {"gidp": "8", "sac": "4", "np": "1307", "sport_code": "afa", "hgnd": "33", "tb": "139", "gidp_opp": "64", "sport_id": "13", "bb": "34", "avg": ".250", "slg": ".424", "team_full": "Modesto Nuts", "ops": ".741", "hbp": "0", "league_full": "California League", "team_abbrev": "MOD", "so": "63", "hfly": "21", "wo": "1", "league_id": "110", "sf": "4", "team_seq": "1", "league": "CAL", "hpop": "0", "cs": "5", "season": "2018", "sb": "2", "go_ao": "1.40", "ppa": "3.53", "player_id": "642451", "ibb": "1", "team_id": "515", "roe": "10", "go": "116", "hr": "11", "rbi": "44", "babip": ".275", "lob": "143", "end_date": "2019-05-24T00:00:00", "xbh": "33", "league_short": "California", "g": "87", "d": "20", "sport": "A(Adv)", "team_short": "Modesto", "tpa": "370", "h": "82", "obp": ".317", "hldr": "28", "t": "2", "ao": "83", "r": "48", "ab": "328"}, {"gidp": "0", "sac": "0", "np": "9", "sport_code": "aaa", "hgnd": "1", "tb": "2", "gidp_opp": "0", "sport_id": "11", "bb": "0", "avg": ".500", "slg": ".500", "team_full": "Tacoma Rainiers", "ops": "1.000", "hbp": "0", "league_full": "Pacific Coast League", "team_abbrev": "TAC", "so": "0", "hfly": "0", "wo": "0", "league_id": "112", "sf": "0", "team_seq": "1", "league": "PCL", "hpop": "0", "cs": "0", "season": "2019", "sb": "0", "go_ao": "*.**", "ppa": "2.25", "player_id": "642451", "ibb": "0", "team_id": "529", "roe": "1", "go": "2", "hr": "0", "rbi": "0", "babip": ".500", "lob": "0", "end_date": "2019-06-05T00:00:00", "xbh": "0", "league_short": "Pacific Coast", "g": "1", "d": "0", "sport": "AAA", "team_short": "Tacoma", "tpa": "4", "h": "2", "obp": ".500", "hldr": "1", "t": "0", "ao": "0", "r": "3", "ab": "4"}, {"gidp": "1", "sac": "3", "np": "708", "sport_code": "afa", "hgnd": "20", "tb": "73", "gidp_opp": "26", "sport_id": "13", "bb": "20", "avg": ".283", "slg": ".440", "team_full": "Modesto Nuts", "ops": ".800", "hbp": "1", "league_full": "California League", "team_abbrev": "MOD", "so": "41", "hfly": "14", "wo": "0", "league_id": "110", "sf": "2", "team_seq": "1", "league": "CAL", "hpop": "0", "cs": "2", "season": "2019", "sb": "4", "go_ao": "0.93", "ppa": "3.69", "player_id": "642451", "ibb": "1", "team_id": "515", "roe": "3", "go": "40", "hr": "7", "rbi": "29", "babip": ".333", "lob": "73", "end_date": "2019-06-20T00:00:00", "xbh": "12", "league_short": "California", "g": "44", "d": "5", "sport": "A(Adv)", "team_short": "Modesto", "tpa": "192", "h": "47", "obp": ".360", "hldr": "13", "t": "0", "ao": "43", "r": "25", "ab": "166"}, {"gidp": "0", "sac": "2", "np": "814", "sport_code": "aax", "hgnd": "20", "tb": "64", "gidp_opp": "26", "sport_id": "12", "bb": "15", "avg": ".237", "slg": ".330", "team_full": "Arkansas Travelers", "ops": ".622", "hbp": "0", "league_full": "Texas League", "team_abbrev": "ARK", "so": "49", "hfly": "3", "wo": "2", "league_id": "109", "sf": "0", "team_seq": "1", "league": "TEX", "hpop": "0", "cs": "1", "season": "2019", "sb": "4", "go_ao": "1.10", "ppa": "3.86", "player_id": "642451", "ibb": "0", "team_id": "574", "roe": "1", "go": "53", "hr": "2", "rbi": "18", "babip": ".308", "lob": "87", "end_date": "2019-09-14T00:00:00", "xbh": "13", "league_short": "Texas", "g": "52", "d": "10", "sport": "AA", "team_short": "Arkansas", "tpa": "211", "h": "46", "obp": ".292", "hldr": "23", "t": "1", "ao": "48", "r": "25", "ab": "194"}]}}, "sport_career_hitting_agg": {"queryResults": {"created": "2019-09-14T18:00:27", "totalSize": "1", "row": {"hr": "45", "gidp": "26", "np": "6275", "sac": "43", "team_count": "8", "sport_code": "min", "hgnd": "203", "rbi": "232", "lob": "923", "babip": ".310", "gidp_opp": "333", "tb": "827", "xbh": "177", "sport_id": "21", "bb": "238", "avg": ".248", "slg": ".392", "ops": ".715", "hbp": "6", "g": "579", "d": "95", "hfly": "142", "so": "540", "wo": "3", "sport": "Minors", "sf": "16", "hpop": "2", "tpa": "2415", "h": "523", "cs": "31", "obp": ".323", "hldr": "176", "t": "37", "ao": "498", "r": "345", "go_ao": "1.28", "sb": "65", "ppa": "2.60", "player_id": "642451", "ab": "2112", "ibb": "5", "roe": "47", "go": "635"}}}, "sport_hitting_agg": {"queryResults": {"created": "2019-09-14T18:00:27", "totalSize": "7", "row": [{"hr": "2", "gidp": "1", "np": "", "sac": "2", "team_count": "1", "popout": "16", "sport_code": "min", "hgnd": "19", "rbi": "17", "lob": "74", "babip": ".327", "gidp_opp": "25", "tb": "72", "xbh": "13", "sport_id": "21", "bb": "23", "avg": ".255", "slg": ".353", "ops": ".691", "hbp": "3", "g": "57", "d": "8", "lineout": "6", "hfly": "20", "so": "50", "flyout": "34", "wo": "0", "sport": "Minors", "sf": "1", "hpop": "1", "tpa": "233", "h": "52", "cs": "8", "obp": ".338", "hldr": "12", "t": "3", "ao": "56", "season": "2013", "r": "39", "go_ao": "0.89", "sb": "14", "ppa": "0.00", "player_id": "642451", "ab": "204", "ibb": "0", "roe": "5", "go": "50"}, {"hr": "2", "gidp": "0", "np": "", "sac": "4", "team_count": "1", "popout": "11", "sport_code": "min", "hgnd": "15", "rbi": "14", "lob": "73", "babip": ".276", "gidp_opp": "22", "tb": "55", "xbh": "11", "sport_id": "21", "bb": "29", "avg": ".211", "slg": ".314", "ops": ".640", "hbp": "1", "g": "49", "d": "6", "lineout": "6", "hfly": "10", "so": "47", "flyout": "29", "wo": "0", "sport": "Minors", "sf": "1", "hpop": "0", "tpa": "210", "h": "37", "cs": "2", "obp": ".325", "hldr": "12", "t": "3", "ao": "46", "season": "2014", "r": "28", "go_ao": "1.09", "sb": "14", "ppa": "0.00", "player_id": "642451", "ab": "175", "ibb": "0", "roe": "5", "go": "50"}, {"hr": "5", "gidp": "6", "np": "121", "sac": "7", "team_count": "3", "popout": "19", "sport_code": "min", "hgnd": "14", "rbi": "31", "lob": "99", "babip": ".288", "gidp_opp": "47", "tb": "89", "xbh": "22", "sport_id": "21", "bb": "26", "avg": ".231", "slg": ".403", "ops": ".711", "hbp": "0", "g": "64", "d": "11", "lineout": "6", "hfly": "15", "so": "59", "flyout": "26", "wo": "0", "sport": "Minors", "sf": "3", "hpop": "0", "tpa": "257", "h": "51", "cs": "3", "obp": ".308", "hldr": "22", "t": "6", "ao": "51", "season": "2015", "r": "37", "go_ao": "1.49", "sb": "11", "ppa": "0.47", "player_id": "642451", "ab": "221", "ibb": "0", "roe": "8", "go": "76"}, {"hr": "2", "gidp": "5", "np": "1577", "sac": "12", "team_count": "1", "popout": "13", "sport_code": "min", "hgnd": "44", "rbi": "29", "lob": "166", "babip": ".347", "gidp_opp": "60", "tb": "137", "xbh": "29", "sport_id": "21", "bb": "47", "avg": ".258", "slg": ".368", "ops": ".709", "hbp": "0", "g": "100", "d": "19", "lineout": "10", "hfly": "19", "so": "100", "flyout": "39", "wo": "0", "sport": "Minors", "sf": "1", "hpop": "0", "tpa": "432", "h": "96", "cs": "2", "obp": ".340", "hldr": "33", "t": "8", "ao": "62", "season": "2016", "r": "65", "go_ao": "2.13", "sb": "4", "ppa": "3.65", "player_id": "642451", "ab": "372", "ibb": "1", "roe": "9", "go": "132"}, {"hr": "14", "gidp": "5", "np": "1739", "sac": "9", "team_count": "2", "popout": "27", "sport_code": "min", "hgnd": "37", "rbi": "50", "lob": "208", "babip": ".313", "gidp_opp": "63", "tb": "196", "xbh": "44", "sport_id": "21", "bb": "44", "avg": ".246", "slg": ".438", "ops": ".749", "hbp": "1", "g": "125", "d": "16", "lineout": "12", "hfly": "40", "so": "131", "flyout": "70", "wo": "0", "sport": "Minors", "sf": "4", "hpop": "1", "tpa": "506", "h": "110", "cs": "8", "obp": ".312", "hldr": "32", "t": "14", "ao": "109", "season": "2017", "r": "75", "go_ao": "1.06", "sb": "12", "ppa": "3.44", "player_id": "642451", "ab": "448", "ibb": "2", "roe": "5", "go": "116"}, {"hr": "11", "gidp": "8", "np": "1307", "sac": "4", "team_count": "1", "popout": "19", "sport_code": "min", "hgnd": "33", "rbi": "44", "lob": "143", "babip": ".275", "gidp_opp": "64", "tb": "139", "xbh": "33", "sport_id": "21", "bb": "34", "avg": ".250", "slg": ".424", "ops": ".741", "hbp": "0", "g": "87", "d": "20", "lineout": "16", "hfly": "21", "so": "63", "flyout": "48", "wo": "1", "sport": "Minors", "sf": "4", "hpop": "0", "tpa": "370", "h": "82", "cs": "5", "obp": ".317", "hldr": "28", "t": "2", "ao": "83", "season": "2018", "r": "48", "go_ao": "1.40", "sb": "2", "ppa": "3.53", "player_id": "642451", "ab": "328", "ibb": "1", "roe": "10", "go": "116"}, {"hr": "9", "gidp": "1", "np": "1531", "sac": "5", "team_count": "3", "popout": "16", "sport_code": "min", "hgnd": "41", "rbi": "47", "lob": "160", "babip": ".322", "gidp_opp": "52", "tb": "139", "xbh": "25", "sport_id": "21", "bb": "35", "avg": ".261", "slg": ".382", "ops": ".708", "hbp": "1", "g": "97", "d": "15", "lineout": "16", "hfly": "17", "so": "90", "flyout": "59", "wo": "2", "sport": "Minors", "sf": "2", "hpop": "0", "tpa": "407", "h": "95", "cs": "3", "obp": ".326", "hldr": "37", "t": "1", "ao": "91", "season": "2019", "r": "53", "go_ao": "1.04", "sb": "8", "ppa": "3.76", "player_id": "642451", "ab": "364", "ibb": "1", "roe": "5", "go": "95"}]}}, "sport_career_hitting_lg": {"queryResults": {"created": "2019-09-14T18:00:27", "totalSize": "8", "row": [{"hr": "0", "gidp": "0", "sac": "0", "team_count": "1", "sport_code": "aaa", "rbi": "0", "tb": "2", "sport_id": "11", "bb": "0", "avg": ".500", "slg": ".500", "league_short": "Pacific Coast", "ops": "1.000", "hbp": "0", "g": "1", "league_full": "Pacific Coast League", "d": "0", "so": "0", "league_id": "112", "sport": "AAA", "sf": "0", "league": "PCL", "h": "2", "cs": "0", "obp": ".500", "t": "0", "ao": "0", "r": "3", "go_ao": "2.00", "sb": "0", "player_id": "642451", "ab": "4", "ibb": "0", "go": "2"}, {"hr": "0", "gidp": "1", "sac": "0", "team_count": "1", "sport_code": "aax", "rbi": "0", "tb": "0", "sport_id": "12", "bb": "0", "avg": ".000", "slg": ".000", "league_short": "Southern", "ops": ".000", "hbp": "0", "g": "3", "league_full": "Southern League", "d": "0", "so": "2", "league_id": "111", "sport": "AA", "sf": "0", "league": "SOU", "h": "0", "cs": "0", "obp": ".000", "t": "0", "ao": "3", "r": "0", "go_ao": "2.00", "sb": "0", "player_id": "642451", "ab": "10", "ibb": "0", "go": "6"}, {"hr": "2", "gidp": "0", "sac": "2", "team_count": "1", "sport_code": "aax", "rbi": "18", "tb": "64", "sport_id": "12", "bb": "15", "avg": ".237", "slg": ".330", "league_short": "Texas", "ops": ".622", "hbp": "0", "g": "52", "league_full": "Texas League", "d": "10", "so": "49", "league_id": "109", "sport": "AA", "sf": "0", "league": "TEX", "h": "46", "cs": "1", "obp": ".292", "t": "1", "ao": "48", "r": "25", "go_ao": "1.10", "sb": "4", "player_id": "642451", "ab": "194", "ibb": "0", "go": "53"}, {"hr": "26", "gidp": "13", "sac": "10", "team_count": "1", "sport_code": "afa", "rbi": "101", "tb": "323", "sport_id": "13", "bb": "75", "avg": ".260", "slg": ".430", "league_short": "California", "ops": ".756", "hbp": "2", "g": "199", "league_full": "California League", "d": "36", "so": "184", "league_id": "110", "sport": "A(Adv)", "sf": "7", "league": "CAL", "h": "195", "cs": "11", "obp": ".326", "t": "7", "ao": "182", "r": "114", "go_ao": "1.20", "sb": "13", "player_id": "642451", "ab": "751", "ibb": "4", "go": "219"}, {"hr": "8", "gidp": "8", "sac": "18", "team_count": "1", "sport_code": "afx", "rbi": "51", "tb": "229", "sport_id": "14", "bb": "72", "avg": ".243", "slg": ".386", "league_short": "Midwest", "ops": ".709", "hbp": "0", "g": "165", "league_full": "Midwest League", "d": "25", "so": "161", "league_id": "118", "sport": "A(Full)", "sf": "4", "league": "MID", "h": "144", "cs": "6", "obp": ".323", "t": "18", "ao": "121", "r": "102", "go_ao": "1.63", "sb": "10", "player_id": "642451", "ab": "593", "ibb": "1", "go": "197"}, {"hr": "5", "gidp": "3", "sac": "7", "team_count": "1", "sport_code": "asx", "rbi": "31", "tb": "82", "sport_id": "15", "bb": "24", "avg": ".260", "slg": ".453", "league_short": "Northwest", "ops": ".794", "hbp": "0", "g": "53", "league_full": "Northwest League", "d": "10", "so": "47", "league_id": "126", "sport": "A(Short)", "sf": "3", "league": "NWL", "h": "47", "cs": "3", "obp": ".341", "t": "5", "ao": "42", "r": "34", "go_ao": "1.38", "sb": "10", "player_id": "642451", "ab": "181", "ibb": "0", "go": "58"}, {"hr": "2", "gidp": "0", "sac": "4", "team_count": "1", "sport_code": "rok", "rbi": "14", "tb": "55", "sport_id": "16", "bb": "29", "avg": ".211", "slg": ".314", "league_short": "Arizona", "ops": ".640", "hbp": "1", "g": "49", "league_full": "Arizona League", "d": "6", "so": "47", "league_id": "121", "sport": "ROK", "sf": "1", "league": "AZL", "h": "37", "cs": "2", "obp": ".325", "t": "3", "ao": "46", "r": "28", "go_ao": "1.09", "sb": "14", "player_id": "642451", "ab": "175", "ibb": "0", "go": "50"}, {"hr": "2", "gidp": "1", "sac": "2", "team_count": "1", "sport_code": "rok", "rbi": "17", "tb": "72", "sport_id": "16", "bb": "23", "avg": ".255", "slg": ".353", "league_short": "Dominican Summer", "ops": ".691", "hbp": "3", "g": "57", "league_full": "Dominican Summer League", "d": "8", "so": "50", "league_id": "130", "sport": "ROK", "sf": "1", "league": "DSL", "h": "52", "cs": "8", "obp": ".338", "t": "3", "ao": "56", "r": "39", "go_ao": "0.89", "sb": "14", "player_id": "642451", "ab": "204", "ibb": "0", "go": "50"}]}}, "proj_pecota_ros_batting": {"queryResults": {"created": "2019-09-14T18:00:27", "totalSize": "0"}}, "index": 5817}